partialtesting/partialtesting.py
partialtesting/partialtesting_cleanup.py
partialtesting-1.0.dist-info/LICENSE
partialtesting-1.0.dist-info/METADATA
partialtesting-1.0.dist-info/WHEEL
partialtesting-1.0.dist-info/entry_points.txt
partialtesting-1.0.dist-info/top_level.txt
partialtesting-1.0.dist-info/RECORD
