Metadata-Version: 2.1
Name: partialtesting
Version: 1.0
Summary: Partial Testing: run only the tests relevant to your changes
Home-page: https://github.com/man-group/partialtesting
Author: MAN Alpha Technology
Author-email: ManAlphaTech@man.com
License: GPLv3+
Keywords: testing,coverage,partialtesting
Platform: UNKNOWN
Classifier: Development Status :: 5 - Production/Stable
Classifier: License :: OSI Approved :: GNU General Public License v3 or later (GPLv3+)
Classifier: Operating System :: OS Independent
Classifier: Programming Language :: Python
Classifier: Topic :: Software Development
Classifier: Programming Language :: Python :: 3
Classifier: Programming Language :: Python :: 3.6
Classifier: Programming Language :: Python :: 3.8
Requires-Dist: click
Provides-Extra: tests
Requires-Dist: pytest ; extra == 'tests'
